wsy_captcha/__init__.py
wsy_captcha/bezier.py
wsy_captcha/comp.py
wsy_captcha/captcha.py
wsy_captcha/image.py
wsy_captcha/fonts/CoasterShadow.ttf
wsy_captcha-1.0.0.dist-info/METADATA
wsy_captcha-1.0.0.dist-info/top_level.txt
wsy_captcha-1.0.0.dist-info/metadata.json
wsy_captcha-1.0.0.dist-info/DESCRIPTION.rst
wsy_captcha-1.0.0.dist-info/WHEEL
wsy_captcha-1.0.0.dist-info/RECORD
