Metadata-Version: 2.0
Name: wsy-captcha
Version: 1.0.0
Summary: A library that generates image captcha.
Home-page: https://github.com/wushuyi/wsy_captcha
Author: wushuyi
Author-email: wushuyi541@gmail.com
License: BSD
Platform: UNKNOWN
Classifier: Environment :: Console
Classifier: Intended Audience :: Developers
Classifier: License :: OSI Approved
Classifier: License :: OSI Approved :: BSD License
Classifier: Operating System :: MacOS
Classifier: Operating System :: POSIX
Classifier: Operating System :: POSIX :: Linux
Classifier: Programming Language :: Python
Classifier: Programming Language :: Python :: 3.4
Classifier: Programming Language :: Python :: Implementation :: CPython
Requires-Dist: Pillow (==3.0.0)
Requires-Dist: six (==1.9.0)
